{
  "sorted_middleware": [],
  "middleware": {
    "/": {
      "files": [
        "server/edge/chunks/_f58e8655._.js",
        "server/edge/chunks/[root-of-the-server]__de110ef0._.js",
        "server/edge/chunks/edge-wrapper_721dd62f.js"
      ],
      "name": "middleware",
      "page": "/",
      "matchers": [
        {
          "regexp": "/:nextData(_next/data/[^/]{1,})?/((?!_next/static|_next/image|favicon.ico|login|signup|landingPage).*){(\\\\.json)}?",
          "originalSource": "/((?!_next/static|_next/image|favicon.ico|login|signup|landingPage).*)"
        }
      ],
      "wasm": [],
      "assets": [],
      "env": {
        "__NEXT_BUILD_ID": "development",
        "NEXT_SERVER_ACTIONS_ENCRYPTION_KEY": "nJt+2zIdE+zCO2t20NzR4FCdYyvNYMgFnDnumwJIXVc=",
        "__NEXT_PREVIEW_MODE_ID": "2d4417a323b3d8eb3d94eeb4e3c97f4d",
        "__NEXT_PREVIEW_MODE_ENCRYPTION_KEY": "b732a9eac4c1344acce5692ed205bf64add5a0a742f67bdc84fe356c13c308c1",
        "__NEXT_PREVIEW_MODE_SIGNING_KEY": "31326ca13140a8ac1a4828e9fc3e8496c6e68bc8a6a60b36eccdd90f8abf8ca3"
      }
    }
  },
  "instrumentation": null,
  "functions": {}
}